LICENSE
MANIFEST.in
README.md
pyproject.toml
setup.py
version.txt
quarto_cli/quarto.py
quarto_cli.egg-info/PKG-INFO
quarto_cli.egg-info/SOURCES.txt
quarto_cli.egg-info/dependency_links.txt
quarto_cli.egg-info/entry_points.txt
quarto_cli.egg-info/requires.txt
quarto_cli.egg-info/top_level.txt