Metadata-Version: 2.4
Name: quarto-cli
Version: 1.8.24
Summary: Open-source scientific and technical publishing system built on Pandoc.
Author: Charles Teague, Carlos Scheidegger
License: MIT License
Project-URL: Homepage, https://www.quarto.org
Project-URL: Source, https://www.github.com/quarto-dev/quarto-cli
Classifier: Development Status :: 5 - Production/Stable
Classifier: Intended Audience :: Developers
Classifier: Intended Audience :: End Users/Desktop
Classifier: Intended Audience :: Information Technology
Classifier: Intended Audience :: Science/Research
Classifier: License :: OSI Approved :: MIT License
Classifier: Operating System :: MacOS :: MacOS X
Classifier: Operating System :: Microsoft :: Windows
Classifier: Operating System :: POSIX :: Linux
Classifier: Programming Language :: Python :: 3.7
Classifier: Programming Language :: Python :: 3.8
Classifier: Programming Language :: Python :: 3.9
Classifier: Programming Language :: Python :: 3.10
Classifier: Programming Language :: Python :: 3.11
Classifier: Programming Language :: Python :: 3.12
License-File: LICENSE
Requires-Dist: jupyter
Requires-Dist: nbclient
Requires-Dist: wheel
Dynamic: license-file
